{
  "name": "Header group",
  "type": "header",
  "sections": {
    "announcement-bar": {
      "type": "announcement-bar",
      "settings": {
        "text": "FREE SHIPPING on orders over $50 — Limited time only!",
        "link_text": "Shop Now",
        "link": "/collections/all",
        "enable_countdown": true,
        "background_color": "#e94560",
        "text_color": "#ffffff"
      }
    },
    "header": {
      "type": "header",
      "settings": {
        "logo_text": "FunShirts.us"
      },
      "blocks": {
        "nav-1": {
          "type": "nav_link",
          "settings": {
            "label": "Shop All",
            "link": "/collections/all"
          }
        },
        "nav-2": {
          "type": "nav_link",
          "settings": {
            "label": "New Arrivals",
            "link": "/collections/frontpage"
          }
        },
        "nav-3": {
          "type": "nav_link",
          "settings": {
            "label": "About",
            "link": "/pages/about"
          }
        },
        "nav-4": {
          "type": "nav_link",
          "settings": {
            "label": "Contact",
            "link": "/pages/contact"
          }
        }
      },
      "block_order": ["nav-1", "nav-2", "nav-3", "nav-4"]
    }
  },
  "order": ["announcement-bar", "header"]
}
